emitcallback/__about__.py
emitcallback/__init__.py
emitcallback/_mod.py
emitcallback-0.1.0.dist-info/METADATA
emitcallback-0.1.0.dist-info/WHEEL
emitcallback-0.1.0.dist-info/licenses/LICENSE.txt
emitcallback-0.1.0.dist-info/RECORD
