Metadata-Version: 2.4
Name: emitcallback
Version: 0.1.0
Project-URL: Documentation, https://pylib-emitcallback.readthedocs.io/en/latest/
Project-URL: Issues, https://github.com/Gianpy16/pylib-emitcallback/issues
Project-URL: Source, https://github.com/Gianpy16/pylib-emitcallback
Author-email: "(GianpyRock) Gianpiero Maggiulli" <gianpieromaggiulli16@gmail.com>
License-Expression: MIT
License-File: LICENSE.txt
Classifier: Development Status :: 4 - Beta
Classifier: Programming Language :: Python
Classifier: Programming Language :: Python :: 3.12
Classifier: Programming Language :: Python :: Implementation :: CPython
Classifier: Programming Language :: Python :: Implementation :: PyPy
Requires-Python: >=3.12
